ssm_admin/__init__.py
ssm_admin/ssm_admin.py
ssm_admin-0.2.0.dist-info/METADATA
ssm_admin-0.2.0.dist-info/WHEEL
ssm_admin-0.2.0.dist-info/entry_points.txt
ssm_admin-0.2.0.dist-info/RECORD
